crawlers/__init__.py
engines/__init__.py
sql/__init__.py
oriondsc_pkg_rioatmadja2018-0.1.1584734226.dist-info/METADATA
oriondsc_pkg_rioatmadja2018-0.1.1584734226.dist-info/WHEEL
oriondsc_pkg_rioatmadja2018-0.1.1584734226.dist-info/top_level.txt
oriondsc_pkg_rioatmadja2018-0.1.1584734226.dist-info/zip-safe
oriondsc_pkg_rioatmadja2018-0.1.1584734226.dist-info/RECORD
