Metadata-Version: 2.1
Name: oriondsc-pkg-rioatmadja2018
Version: 0.1.1584734226
Summary: Engines to collect data.
Home-page: UNKNOWN
Author: Rio Atmadja
Author-email: rioatmadja2018@gmail.com
License: UNKNOWN
Platform: UNKNOWN
Classifier: Programming Language :: Python :: 3
Classifier: Operating System :: OS Independent
Classifier: Intended Audience :: Developers
Requires-Python: >=3.6
Requires-Dist: joblib (==0.14.1)
Requires-Dist: numpy (==1.18.2)
Requires-Dist: pandas (==1.0.3)
Requires-Dist: python-dateutil (==2.8.1)
Requires-Dist: pytz (==2019.3)
Requires-Dist: scikit-learn (==0.22.2.post1)
Requires-Dist: scipy (==1.4.1)
Requires-Dist: six (==1.14.0)
Requires-Dist: sklearn (==0.0)
